task-tracker-cli/__init__.py
task-tracker-cli/main.py
task_tracker_cli/__init__.py
task_tracker_cli/main.py
task_tracker_cli-0.1.0.3.dist-info/LICENSE
task_tracker_cli-0.1.0.3.dist-info/METADATA
task_tracker_cli-0.1.0.3.dist-info/WHEEL
task_tracker_cli-0.1.0.3.dist-info/entry_points.txt
task_tracker_cli-0.1.0.3.dist-info/top_level.txt
task_tracker_cli-0.1.0.3.dist-info/RECORD
