Metadata-Version: 2.1
Name: task-tracker-cli
Version: 0.1.0.3
Summary: A simple CLI tool for managing tasks.
Home-page: https://github.com/under-script/task-tracker-cli
Author: Yunusov Abdulmajid
Author-email: abdulmajidyunusov18@gmail.com
License: MIT
Project-URL: Bug Reports, https://github.com/under-script/task-tracker-cli/issues
Project-URL: Source, https://github.com/under-script/task-tracker-cli
Classifier: License :: OSI Approved :: MIT License
Classifier: Programming Language :: Python
Classifier: Programming Language :: Python :: 3
Classifier: Programming Language :: Python :: 3.6
Classifier: Programming Language :: Python :: 3.7
Classifier: Programming Language :: Python :: 3.8
Classifier: Programming Language :: Python :: 3.9
Classifier: Programming Language :: Python :: 3.10
Classifier: Programming Language :: Python :: Implementation :: CPython
Classifier: Programming Language :: Python :: Implementation :: PyPy
Classifier: Development Status :: 4 - Beta
Classifier: Intended Audience :: Developers
Classifier: Topic :: Software Development :: Libraries :: Python Modules
Classifier: Environment :: Console
Requires-Python: >=3.6.0
License-File: LICENSE
Requires-Dist: click
Requires-Dist: prettytable
